cfgclasses/__init__.py
cfgclasses/arghelper.py
cfgclasses/argspec.py
cfgclasses/configclass.py
cfgclasses/py.typed
cfgclasses/transforms.py
cfgclasses/validation.py
cfgclasses/test/__init__.py
cfgclasses/test/test_argspec.py
cfgclasses/test/test_configclass.py
cfgclasses/test/test_deprecated_api.py
cfgclasses/test/test_transforms.py
cfgclasses/test/test_typing.py
cfgclasses-2.4.0.dist-info/METADATA
cfgclasses-2.4.0.dist-info/WHEEL
cfgclasses-2.4.0.dist-info/licenses/LICENSE
cfgclasses-2.4.0.dist-info/RECORD
