Metadata-Version: 2.4
Name: cfgclasses
Version: 2.4.0
Summary: Strongly typed tool configuration classes for argument parsing.
Project-URL: Homepage, https://github.com/ollij93/cfgclasses
Project-URL: Bug Tracker, https://github.com/ollij93/cfgclasses/issues
Author-email: Olli Johnson <ollijohnson93@gmail.com>
License-File: LICENSE
Classifier: License :: OSI Approved :: MIT License
Classifier: Operating System :: OS Independent
Classifier: Programming Language :: Python :: 3
Requires-Python: >=3.10
